gptimpl/__init__.py
gptimpl/ai_codegen.py
gptimpl/collector.py
gptimpl/main.py
gptimpl-0.1.1.dist-info/LICENSE
gptimpl-0.1.1.dist-info/METADATA
gptimpl-0.1.1.dist-info/WHEEL
gptimpl-0.1.1.dist-info/entry_points.txt
gptimpl-0.1.1.dist-info/RECORD
