Metadata-Version: 2.1
Name: gptimpl
Version: 0.1.1
Summary: Ask ChatGPT to implement your existing python functions.
Home-page: https://github.com/aalekhpatel07/gptimpl
License: LICENSE
Author: Aalekh Patel
Author-email: aalekh.gwpeck.7998@icloud.com
Requires-Python: >=3.9,<4.0
Classifier: License :: Other/Proprietary License
Classifier: Programming Language :: Python :: 3
Classifier: Programming Language :: Python :: 3.9
Classifier: Programming Language :: Python :: 3.10
Classifier: Programming Language :: Python :: 3.11
Requires-Dist: astor (==0.8.1)
Requires-Dist: openai (==0.27.2)
Project-URL: Repository, https://github.com/aalekhpatel07/gptimpl
